gooey_gpu.py
gooey_gpu-1.0.1.dist-info/METADATA
gooey_gpu-1.0.1.dist-info/WHEEL
gooey_gpu-1.0.1.dist-info/licenses/LICENSE.md
gooey_gpu-1.0.1.dist-info/RECORD
