Metadata-Version: 2.4
Name: gooey-gpu
Version: 1.0.1
Summary: 
License-File: LICENSE.md
Author: Dev Aggarwal
Author-email: devxpy@gmail.com
Requires-Python: >=3.10
Classifier: Programming Language :: Python :: 3
Classifier: Programming Language :: Python :: 3.10
Classifier: Programming Language :: Python :: 3.11
Classifier: Programming Language :: Python :: 3.12
Classifier: Programming Language :: Python :: 3.13
Classifier: Programming Language :: Python :: 3.14
